django_oscar_dsd/__init__.py
django_oscar_dsd/admin.py
django_oscar_dsd/apps.py
django_oscar_dsd/functions.py
django_oscar_dsd/models.py
django_oscar_dsd/serializers.py
django_oscar_dsd/settings.py
django_oscar_dsd/skeleton.py
django_oscar_dsd/tasks.py
django_oscar_dsd/tests.py
django_oscar_dsd/utils.py
django_oscar_dsd/backend/__init__.py
django_oscar_dsd/backend/models.py
django_oscar_dsd/dashboard/__init__.py
django_oscar_dsd/dashboard/apps.py
django_oscar_dsd/dashboard/forms.py
django_oscar_dsd/dashboard/urls.py
django_oscar_dsd/dashboard/views.py
django_oscar_dsd/fixtures/categories.json
django_oscar_dsd/fixtures/products0.json
django_oscar_dsd/fixtures/products1.json
django_oscar_dsd/fixtures/products2.json
django_oscar_dsd/fixtures/products3.json
django_oscar_dsd/fixtures/products4.json
django_oscar_dsd/fixtures/products5.json
django_oscar_dsd/migrations/0001_initial.py
django_oscar_dsd/migrations/__init__.py
django_oscar_dsd/templates/dsd/dashboard/dsd_product_delete.html
django_oscar_dsd/templates/dsd/dashboard/dsd_product_form.html
django_oscar_dsd/templates/dsd/dashboard/dsd_product_list.html
django_oscar_dsd/templates/dsd/dashboard/dsd_product_publish.html
django_oscar_dsd/templates/dsd/dashboard/partials/form.html
django_oscar_dsd-0.0.2.dist-info/AUTHORS.rst
django_oscar_dsd-0.0.2.dist-info/LICENSE.txt
django_oscar_dsd-0.0.2.dist-info/METADATA
django_oscar_dsd-0.0.2.dist-info/WHEEL
django_oscar_dsd-0.0.2.dist-info/entry_points.txt
django_oscar_dsd-0.0.2.dist-info/top_level.txt
django_oscar_dsd-0.0.2.dist-info/RECORD
