Metadata-Version: 2.1
Name: django-oscar-dsd
Version: 0.0.2
Summary: Django Oscar DSD integration
Home-page: https://bitbucket.org/pai/django-oscar-dsd
Author: pai
Author-email: paiuolo@gmail.com
License: mit
Project-URL: Documentation, https://pyscaffold.org/
Platform: any
Classifier: Development Status :: 4 - Beta
Classifier: Programming Language :: Python
Requires-Dist: requests
Requires-Dist: django
Requires-Dist: django-oscar
Requires-Dist: djangorestframework
Provides-Extra: testing
Requires-Dist: pytest ; extra == 'testing'
Requires-Dist: pytest-cov ; extra == 'testing'
